{
  "kind": "collectionType",
  "collectionName": "steps",
  "info": {
    "singularName": "step",
    "pluralName": "steps",
    "displayName": "Step",
    "description": ""
  },
  "options": {
    "draftAndPublish": true
  },
  "pluginOptions": {},
  "attributes": {
    "title": {
      "type": "string"
    },
    "image_url": {
      "type": "media",
      "multiple": true,
      "required": false,
      "allowedTypes": [
        "images",
        "files",
        "videos",
        "audios"
      ]
    },
    "question": {
      "type": "relation",
      "relation": "manyToOne",
      "target": "api::question.question",
      "inversedBy": "steps"
    },
    "result": {
      "type": "customField",
      "options": {
        "preset": "defaultHtml"
      },
      "customField": "plugin::ckeditor5.CKEditor"
    }
  }
}
